norwegian_forest_cat/__init__.py
norwegian_forest_cat/cat_method.py
norwegian_forest_cat-0.0.5.dist-info/LICENSE
norwegian_forest_cat-0.0.5.dist-info/WHEEL
norwegian_forest_cat-0.0.5.dist-info/METADATA
norwegian_forest_cat-0.0.5.dist-info/RECORD
