Metadata-Version: 2.1
Name: norwegian-forest-cat
Version: 0.0.5
Summary: A small example package
License: MIT
Author: chiawei chang
Author-email: williamcw.chang@moxa.com
Requires-Python: >=3.7,<4.0
Classifier: License :: OSI Approved :: MIT License
Classifier: Programming Language :: Python :: 3
Classifier: Programming Language :: Python :: 3.7
Classifier: Programming Language :: Python :: 3.8
Requires-Dist: requests (>=2.24.0,<3.0.0)
